MANIFEST.in
requirements.txt
setup.py
rio_toa/__init__.py
rio_toa/brightness_temp.py
rio_toa/radiance.py
rio_toa/reflectance.py
rio_toa/sun_utils.py
rio_toa/toa_utils.py
rio_toa.egg-info/PKG-INFO
rio_toa.egg-info/SOURCES.txt
rio_toa.egg-info/dependency_links.txt
rio_toa.egg-info/entry_points.txt
rio_toa.egg-info/not-zip-safe
rio_toa.egg-info/requires.txt
rio_toa.egg-info/top_level.txt
rio_toa/scripts/__init__.py
rio_toa/scripts/cli.py