Metadata-Version: 1.0
Name: rio-toa
Version: 0.3.0
Summary: Top Of Atmosphere (TOA) calculations for Landsat 8
Home-page: https://github.com/mapbox/rio-toa
Author: Damon Burgett
Author-email: damon@mapbox.com
License: BSD
Platform: UNKNOWN
